filery/__init__.py
filery/byteify.py
filery/collection.py
filery/dirs.py
filery/files.py
filery/finders.py
filery/info.py
filery/paths.py
filery/processors.py
filery/utils.py
filery/videos.py
filery/ffmpeg_wrapper/__init__.py
filery/ffmpeg_wrapper/probe.py
filery/ffmpeg_wrapper/utils.py
filery/ffmpeg_wrapper/parsers/__init__.py
filery/ffmpeg_wrapper/parsers/fields.py
filery/ffmpeg_wrapper/parsers/video_info_parser.py
filery-0.26.dist-info/DESCRIPTION.rst
filery-0.26.dist-info/METADATA
filery-0.26.dist-info/RECORD
filery-0.26.dist-info/WHEEL
filery-0.26.dist-info/metadata.json
filery-0.26.dist-info/top_level.txt
