Metadata-Version: 2.0
Name: filery
Version: 0.26
Summary: File Path API for Python.
Home-page: https://github.com/GabrielC101/filer
Author: Gabriel Curio
Author-email: UNKNOWN
License: UNKNOWN
Keywords: system,linux
Platform: UNKNOWN
Requires-Dist: marshmallow
Requires-Dist: python-magic
Requires-Dist: six
Requires-Dist: xxhash
